genbenchsite/__init__.py
genbenchsite/html_template/aboutContent.html
genbenchsite/html_template/footer.html
genbenchsite/html_template/googleAnalytics.html
genbenchsite/html_template/header.html
genbenchsite/html_template/library.html
genbenchsite/html_template/navigation.html
genbenchsite/html_template/presentation.html
genbenchsite/html_template/rankBar.html
genbenchsite/html_template/task.html
genbenchsite/html_template/theme.html
genbenchsite/src/.template.txt
genbenchsite/src/__init__.py
genbenchsite/src/benchmark.py
genbenchsite/src/benchsite.py
genbenchsite/src/collectCode.py
genbenchsite/src/getMachineData.py
genbenchsite/src/json_to_python_object.py
genbenchsite/src/library.py
genbenchsite/src/logger.py
genbenchsite/src/main.py
genbenchsite/src/ranking.py
genbenchsite/src/static_site_generator.py
genbenchsite/src/structure_test.py
genbenchsite/src/task.py
genbenchsite/src/template.py
genbenchsite/website_template/__init__.py
genbenchsite/website_template/assets/bullseye.svg
genbenchsite/website_template/assets/chevron-down-solid.svg
genbenchsite/website_template/assets/clipboard-list.svg
genbenchsite/website_template/assets/discord.svg
genbenchsite/website_template/assets/envelope-solid.svg
genbenchsite/website_template/assets/github.svg
genbenchsite/website_template/assets/gitlab.svg
genbenchsite/website_template/assets/question.svg
genbenchsite/website_template/assets/twitter.svg
genbenchsite/website_template/script/arrowRank.js
genbenchsite/website_template/script/complexePlot.js
genbenchsite/website_template/script/dynamicPlot.js
genbenchsite/website_template/script/groupedBarChart.js
genbenchsite/website_template/script/heatMapChart.js
genbenchsite/website_template/script/histogram.js
genbenchsite/website_template/script/libraryScript.js
genbenchsite/website_template/script/rankBar.js
genbenchsite/website_template/script/taskScript.js
genbenchsite/website_template/script/themeScript.js
genbenchsite/website_template/script/violonsChart.js
genbenchsite-0.0.9.dist-info/METADATA
genbenchsite-0.0.9.dist-info/WHEEL
genbenchsite-0.0.9.dist-info/entry_points.txt
genbenchsite-0.0.9.dist-info/top_level.txt
genbenchsite-0.0.9.dist-info/RECORD
