Metadata-Version: 2.1
Name: genbenchsite
Version: 0.0.9
Summary: Generate a benchmark website from a set of benchmark tests
Home-page: https://white-on.github.io/GenBenchSite/
Author: Jules Cassan
Author-email: jules.cassan@hotmail.com
Project-URL: Github, https://github.com/White-On/GenBenchSite
Requires-Python: >=3.9
Requires-Dist: colorama (>=0.4.6)
Requires-Dist: Jinja2 (>=3.1.2)
Requires-Dist: MarkupSafe (>=2.1.2)
Requires-Dist: numpy (>=1.24.2)
Requires-Dist: psutil (>=5.9.5)
Requires-Dist: Pygments (>=2.15.1)
Requires-Dist: tqdm (>=4.65.0)
Requires-Dist: rich (>=12.5.1)
Provides-Extra: dev
Requires-Dist: twine (>=4.0.2) ; extra == 'dev'
